{
    "imagePath": "01113.jpg",
    "imageHeight": 3888,
    "imageWidth": 5184,
    "lps": [
        {
            "lp_id": "AD-398*B*B",
            "poly_coord": [
                [
                    3510,
                    1284
                ],
                [
                    4570,
                    1222
                ],
                [
                    4603,
                    1438
                ],
                [
                    3538,
                    1501
                ]
            ],
            "characters": [
                {
                    "char_id": "3",
                    "bbox_coord": [
                        [
                            3671,
                            1285
                        ],
                        [
                            3787,
                            1456
                        ]
                    ]
                },
                {
                    "char_id": "9",
                    "bbox_coord": [
                        [
                            3792,
                            1278
                        ],
                        [
                            3910,
                            1454
                        ]
                    ]
                },
                {
                    "char_id": "8",
                    "bbox_coord": [
                        [
                            3912,
                            1271
                        ],
                        [
                            4029,
                            1435
                        ]
                    ]
                },
                {
                    "char_id": "B",
                    "bbox_coord": [
                        [
                            4196,
                            1250
                        ],
                        [
                            4319,
                            1433
                        ]
                    ]
                },
                {
                    "char_id": "B",
                    "bbox_coord": [
                        [
                            4433,
                            1243
                        ],
                        [
                            4543,
                            1422
                        ]
                    ]
                }
            ]
        }
    ]
}