[
  {
    "path": "/ramajoballester/UC3M-LP",
    "title": "ramajoballester/UC3M-LP: UC3M License Plate detection and recognition dataset",
    "count": 45,
    "uniques": 32
  },
  {
    "path": "/ramajoballester/UC3M-LP/tree/main/sample",
    "title": "UC3M-LP/sample at main · ramajoballester/UC3M-LP · GitHub",
    "count": 22,
    "uniques": 6
  },
  {
    "path": "/ramajoballester/UC3M-LP/tree/main/scripts",
    "title": "UC3M-LP/scripts at main · ramajoballester/UC3M-LP · GitHub",
    "count": 16,
    "uniques": 6
  },
  {
    "path": "/ramajoballester/UC3M-LP/tree/main/cfg",
    "title": "UC3M-LP/cfg at main · ramajoballester/UC3M-LP · GitHub",
    "count": 15,
    "uniques": 5
  },
  {
    "path": "/ramajoballester/UC3M-LP/blob/main/docs/dataset.png",
    "title": "UC3M-LP/docs/dataset.png at main · ramajoballester/UC3M-LP · GitHub",
    "count": 10,
    "uniques": 4
  },
  {
    "path": "/ramajoballester/UC3M-LP/blob/main/sample/00026.jpg",
    "title": "UC3M-LP/sample/00026.jpg at main · ramajoballester/UC3M-LP · GitHub",
    "count": 9,
    "uniques": 4
  },
  {
    "path": "/ramajoballester/UC3M-LP/blob/main/cfg/UC3M-LP-lp.yaml",
    "title": "UC3M-LP/cfg/UC3M-LP-lp.yaml at main · ramajoballester/UC3M-LP · GitHub",
    "count": 9,
    "uniques": 1
  },
  {
    "path": "/ramajoballester/UC3M-LP/tree/main/docs",
    "title": "UC3M-LP/docs at main · ramajoballester/UC3M-LP · GitHub",
    "count": 7,
    "uniques": 3
  },
  {
    "path": "/ramajoballester/UC3M-LP/tree/main",
    "title": "ramajoballester/UC3M-LP: UC3M License Plate detection and recognition dataset",
    "count": 5,
    "uniques": 2
  },
  {
    "path": "/ramajoballester/UC3M-LP/blob/main/requirements.txt",
    "title": "UC3M-LP/requirements.txt at main · ramajoballester/UC3M-LP · GitHub",
    "count": 4,
    "uniques": 2
  }
]